seauval/__init__.py
seauval/evaluations.py
seauval/groups.py
seauval/manager.py
seauval/randomizer.py
seauval/tools.py
seauval-0.9.1.data/scripts/manager.py
seauval-0.9.1.dist-info/METADATA
seauval-0.9.1.dist-info/WHEEL
seauval-0.9.1.dist-info/top_level.txt
seauval-0.9.1.dist-info/RECORD
