Metadata-Version: 2.1
Name: seauval
Version: 0.9.1
Home-page: https://gitlab.com/ludovic.hofer/sae
Author: Ludovic Hofer
Author-email: medrimonia@gmail.com
Classifier: Programming Language :: Python :: 3
Classifier: License :: OSI Approved :: MIT License
Classifier: Operating System :: OS Independent
